{
  "version": "cicsc/phase29-exit-checklist-v1",
  "timestamp_unix": 1770996085,
  "items": [
    {
      "id": "scope_baseline_status",
      "artifact": "docs/pilot/phase29-status-register.json",
      "status": "pass"
    },
    {
      "id": "assurance_expansion_status",
      "artifact": "docs/pilot/phase29-assurance-expansion-closure-report.json",
      "status": "pass"
    },
    {
      "id": "governance_continuity_status",
      "artifact": "docs/pilot/phase29-governance-continuity-closure-report.json",
      "status": "pass"
    },
    {
      "id": "governance_harness_status",
      "artifact": "docs/pilot/phase29-governance-continuity-harnesses.json",
      "status": "pass"
    }
  ],
  "overall": "pass"
}
