{
  "version": "cicsc/phase13-closure-report-v1",
  "timestamp_unix": 1771062300,
  "inputs": {
    "exit_checklist": "docs/pilot/phase13-exit-checklist.json",
    "doc_consistency": "docs/pilot/phase13-doc-consistency.json",
    "phase14_gate": "docs/pilot/phase14-gate.json",
    "scale_envelope": "docs/pilot/phase13-scale-envelope-report.json",
    "hardening": "docs/pilot/phase13-hardening-closure-report.json"
  },
  "status": "pass",
  "summary": {
    "scope_baseline_governance": "pass",
    "scale_envelope": "pass",
    "hardening": "pass",
    "phase14_gate_state": "open_when_checklist_pass"
  },
  "exit_criteria": [
    { "id": "P13_EXIT_SCOPE_BASELINE", "status": "pass" },
    { "id": "P13_EXIT_SCALE_ENVELOPE", "status": "pass" },
    { "id": "P13_EXIT_HARDENING", "status": "pass" },
    { "id": "P13_EXIT_GOVERNANCE", "status": "pass" },
    { "id": "P13_EXIT_PHASE14_GATE", "status": "pass" }
  ]
}
